iputils/__init__.py
tests/__init__.py
tests/test_IPUtils.py
iputils-0.5.7.dist-info/LICENSE.md
iputils-0.5.7.dist-info/METADATA
iputils-0.5.7.dist-info/WHEEL
iputils-0.5.7.dist-info/top_level.txt
iputils-0.5.7.dist-info/RECORD
