Metadata-Version: 2.1
Name: iputils
Version: 0.5.7
Summary: wrapper of ipaddress.py, easy to use
Home-page: https://github.com/hezhiming/iputils
Author: he.zhiming
Author-email: he.zhiming@foxmail.com
License: MIT
Keywords: IPv4,IPv6
Platform: any
Classifier: Development Status :: 5 - Production/Stable
Classifier: Intended Audience :: Developers
Classifier: License :: OSI Approved :: MIT License
Classifier: Operating System :: OS Independent
